redmineci/__init__.py
redmineci/main.py
redmineci/redmineci.py
redmineci/requirements.txt
redmine_ci-0.2.5.dist-info/LICENSE.md
redmine_ci-0.2.5.dist-info/METADATA
redmine_ci-0.2.5.dist-info/WHEEL
redmine_ci-0.2.5.dist-info/entry_points.txt
redmine_ci-0.2.5.dist-info/top_level.txt
redmine_ci-0.2.5.dist-info/RECORD
