Metadata-Version: 2.1
Name: redmine-ci
Version: 0.2.5
Summary: Solve Redmine Status by Gitlab CI
Home-page: http://gitlab.khomp.corp/uilian/redmine-ci
Author: Khomp
Author-email: iot@khomp.com
License: MIT
Keywords: gitlab,ci,gitlab-ci,redmine,issue-tracker
Platform: UNKNOWN
Classifier: Development Status :: 4 - Beta
Classifier: Intended Audience :: Developers
Classifier: Topic :: Software Development :: Build Tools
Classifier: License :: OSI Approved :: MIT License
Classifier: Programming Language :: Python :: 2
Classifier: Programming Language :: Python :: 2.7
Classifier: Programming Language :: Python :: 3
Classifier: Programming Language :: Python :: 3.6
Requires-Dist: requests (>=2.19.1)
Requires-Dist: colorama (>=0.3.9)
Requires-Dist: termcolor (>=1.1.0)
